{"DomsatSeq":7967,"DomsatTime":0,"CarrierStart":"2023-03-13T10:45:00+00:00","CarrierStop":"2023-03-13T10:45:03+00:00","Baud":300,"GoodPhasePct":100,"FreqOffset":-0.3,"SignalStrength":39.9,"PhaseNoise":2.25,"LocalRecvTime":"2023-03-13T10:45:14+00:00","BinaryMsg":"MzNBMDc0N0UyMzA3MjEwNDUwMEc0MC0wTk4wNjlFVVAwMDA4MSJQODcyMjk1NjFCcWNAR0BAZDBZP0o4QHhiQEJAI0B4XjRDZjVEQzZhXz1BPzxCQzJAUnFAQkEiQFJ0PEJDIGRUSmZOQXlBd0F1QXdBdkF1IA==","flags":"0x00081855","platformId":"33A0747E","sat":"goes","DecodedData":{"Platform":"87229561-South Port Everglades (DCP 1)","TransportMedium":"goes-33A0747E","Station":"87229561","Sensors":[{"Sensor":"Air Temperature D1","ParameterCode":"D1","Values":[230.0]},{"Sensor":"Water Temperature E1","ParameterCode":"E1","Values":[259.0]},{"Sensor":"Barometric Pressure F1","ParameterCode":"F1","Values":[2943.0]},{"Sensor":"ANALOG SENSOR 1","ParameterCode":"L1","Values":[131.0]},{"Sensor":"ANALOG SENSOR 2","ParameterCode":"M1","Values":[127.0]},{"Sensor":"Tsunami WL U1","ParameterCode":"U1","Values":[3621.0,3619.0,3617.0,3619.0,3618.0,3617.0]},{"Sensor":"Microwave WL Y1","ParameterCode":"Y1","Values":[3614.0]},{"Sensor":"Backup WL B1","ParameterCode":"B1","Values":[1204.0]},{"Sensor":"ANALOG SENSOR 1","ParameterCode":"L1","Values":[131.0]}],"EndTime":"2023-03-13 10:36:00.000+0000"}}