{"DomsatSeq":85406,"DomsatTime":0,"CarrierStart":"2023-05-15T12:15:00+00:00","CarrierStop":"2023-05-15T12:15:03+00:00","Baud":300,"GoodPhasePct":100,"FreqOffset":-1.6,"SignalStrength":40.2,"PhaseNoise":2.05,"LocalRecvTime":"2023-05-15T12:15:06+00:00","BinaryMsg":"MzNBMDc0N0UyMzEzNTEyMTUwMEc0MC0wTk4wNjlFVUIwMDA4MSJQODcyMjk1NjFCcWNAR0BARjBafkw4QHVaQEdAI0B1RjRESDVFXDZiUT1CQjxCRjJAVG9AQ0EiQFR+PEJJIGdUTEhNQnJCb0JpQmdCYkJgIA==","flags":"0x00081855","platformId":"33A0747E","sat":"goes","agency":"NOANOS","DecodedData":{"Platform":"87229561-South Port Everglades (DCP 1)","TransportMedium":"goes-33A0747E","Station":"87229561","Sensors":[{"Sensor":"Air Temperature D1","ParameterCode":"D1","Values":[264.0]},{"Sensor":"Water Temperature E1","ParameterCode":"E1","Values":[348.0]},{"Sensor":"Barometric Pressure F1","ParameterCode":"F1","Values":[2993.0]},{"Sensor":"ANALOG SENSOR 1","ParameterCode":"L1","Values":[134.0]},{"Sensor":"ANALOG SENSOR 2","ParameterCode":"M1","Values":[130.0]},{"Sensor":"Tsunami WL U1","ParameterCode":"U1","Values":[3428.0,3425.0,3419.0,3417.0,3412.0,3410.0]},{"Sensor":"Microwave WL Y1","ParameterCode":"Y1","Values":[3398.0]},{"Sensor":"Backup WL B1","ParameterCode":"B1","Values":[1342.0]},{"Sensor":"ANALOG SENSOR 1","ParameterCode":"L1","Values":[137.0]}],"EndTime":"2023-05-15 12:06:00.000+0000"}}