{"DomsatSeq":88342,"DomsatTime":0,"CarrierStart":"2023-03-28T06:51:00+00:00","CarrierStop":"2023-03-28T06:51:03+00:00","Baud":300,"GoodPhasePct":99.7,"FreqOffset":-0.8,"SignalStrength":39.8,"PhaseNoise":2.42,"LocalRecvTime":"2023-03-28T06:51:05+00:00","BinaryMsg":"MzNBMDc0N0UyMzA4NzA2NTEwMEc0MC0wTk4wNjlFVUIwMDA4MSJQODcyMjk1NjFCcWNAR0BAajBaTkY4QHNVQEJAI0BzVDRDeTVEaDZiTT1CQDxCRDJAVklAQkEiQFZLPEJEIGVURmxNQGVAZ0BkQGJAYUBiIA==","flags":"0x00081855","platformId":"33A0747E","sat":"goes","DecodedData":{"Platform":"87229561-South Port Everglades (DCP 1)","TransportMedium":"goes-33A0747E","Station":"87229561","Sensors":[{"Sensor":"Air Temperature D1","ParameterCode":"D1","Values":[249.0]},{"Sensor":"Water Temperature E1","ParameterCode":"E1","Values":[296.0]},{"Sensor":"Barometric Pressure F1","ParameterCode":"F1","Values":[2989.0]},{"Sensor":"ANALOG SENSOR 1","ParameterCode":"L1","Values":[132.0]},{"Sensor":"ANALOG SENSOR 2","ParameterCode":"M1","Values":[128.0]},{"Sensor":"Tsunami WL U1","ParameterCode":"U1","Values":[3287.0,3289.0,3286.0,3284.0,3283.0,3284.0]},{"Sensor":"Microwave WL Y1","ParameterCode":"Y1","Values":[3284.0]},{"Sensor":"Backup WL B1","ParameterCode":"B1","Values":[1419.0]},{"Sensor":"ANALOG SENSOR 1","ParameterCode":"L1","Values":[132.0]}],"EndTime":"2023-03-28 06:42:00.000+0000"}}