{"DomsatSeq":97092,"DomsatTime":0,"CarrierStart":"2023-04-23T05:27:00+00:00","CarrierStop":"2023-04-23T05:27:03+00:00","Baud":300,"GoodPhasePct":100,"FreqOffset":-4.4,"SignalStrength":39.1,"PhaseNoise":2.54,"LocalRecvTime":"2023-04-23T05:27:05+00:00","BinaryMsg":"MzNBMDc0N0UyMzExMzA1MjcwMEczOS0wTk4wNjlFVUIwMDA4MSJQODcyMjk1NjFCcWNAR0BAUjBaaEU4QHF6QERAI0BxajREQTVFUzZhTD1CQDxCRDJAV0tAQ0AiQFdYPEJEIGVURVRMQ0hDRkNEQ0JCfkJ9IA==","flags":"0x00081855","platformId":"33A0747E","sat":"goes","agency":"NOANOS","DecodedData":{"Platform":"87229561-South Port Everglades (DCP 1)","TransportMedium":"goes-33A0747E","Station":"87229561","Sensors":[{"Sensor":"Air Temperature D1","ParameterCode":"D1","Values":[257.0]},{"Sensor":"Water Temperature E1","ParameterCode":"E1","Values":[339.0]},{"Sensor":"Barometric Pressure F1","ParameterCode":"F1","Values":[2924.0]},{"Sensor":"ANALOG SENSOR 1","ParameterCode":"L1","Values":[132.0]},{"Sensor":"ANALOG SENSOR 2","ParameterCode":"M1","Values":[128.0]},{"Sensor":"Tsunami WL U1","ParameterCode":"U1","Values":[3200.0,3198.0,3196.0,3194.0,3190.0,3189.0]},{"Sensor":"Microwave WL Y1","ParameterCode":"Y1","Values":[3178.0]},{"Sensor":"Backup WL B1","ParameterCode":"B1","Values":[1496.0]},{"Sensor":"ANALOG SENSOR 1","ParameterCode":"L1","Values":[132.0]}],"EndTime":"2023-04-23 05:18:00.000+0000"}}