{"DomsatSeq":13652,"DomsatTime":0,"CarrierStart":"2023-04-06T01:03:00+00:00","CarrierStop":"2023-04-06T01:03:03+00:00","Baud":300,"GoodPhasePct":99.7,"FreqOffset":-1.5,"SignalStrength":39.9,"PhaseNoise":2.23,"LocalRecvTime":"2023-04-06T01:05:16+00:00","BinaryMsg":"MzNBMDc0N0UyMzA5NjAxMDMwMEc0MC0wTk4wNjlFVUIwMDA4MSJQODcyMjk1NjFCcWNAR0BAdjBaV0A4QHBEQEdDI0BwRTRERjVEPzZiYT1CQDxCRDJAWGJAQ0AiQFhhPEJFIGVUQHhMQUxBTEFQQU1BSkFHIA==","flags":"0x00081855","platformId":"33A0747E","sat":"goes","DecodedData":{"Platform":"87229561-South Port Everglades (DCP 1)","TransportMedium":"goes-33A0747E","Station":"87229561","Sensors":[{"Sensor":"Air Temperature D1","ParameterCode":"D1","Values":[262.0]},{"Sensor":"Water Temperature E1","ParameterCode":"E1","Values":[319.0]},{"Sensor":"Barometric Pressure F1","ParameterCode":"F1","Values":[3009.0]},{"Sensor":"ANALOG SENSOR 1","ParameterCode":"L1","Values":[132.0]},{"Sensor":"ANALOG SENSOR 2","ParameterCode":"M1","Values":[128.0]},{"Sensor":"Tsunami WL U1","ParameterCode":"U1","Values":[3076.0,3076.0,3080.0,3077.0,3074.0,3071.0]},{"Sensor":"Microwave WL Y1","ParameterCode":"Y1","Values":[3077.0]},{"Sensor":"Backup WL B1","ParameterCode":"B1","Values":[1569.0]},{"Sensor":"ANALOG SENSOR 1","ParameterCode":"L1","Values":[133.0]}],"EndTime":"2023-04-06 00:54:00.000+0000"}}