{"DomsatSeq":99378,"DomsatTime":0,"CarrierStart":"2023-03-28T16:15:00+00:00","CarrierStop":"2023-03-28T16:15:03+00:00","Baud":300,"GoodPhasePct":100,"FreqOffset":-2.4,"SignalStrength":40.6,"PhaseNoise":1.96,"LocalRecvTime":"2023-03-28T16:15:05+00:00","BinaryMsg":"MzNBMDc0N0UyMzA4NzE2MTUwMEc0MS0wTk4wNjlFVVAwMDA4MSJQODcyMjk1NjFCcWNAR0BARjBaTlA4QHZIQEpCI0B2YjRESDVEajZiWD1CSjxCTDJAVFJARUAiQFRBPEJLIG1UUEhNQ1dDS0NPQ1JDX0NZIA==","flags":"0x00081855","platformId":"33A0747E","sat":"goes","DecodedData":{"Platform":"87229561-South Port Everglades (DCP 1)","TransportMedium":"goes-33A0747E","Station":"87229561","Sensors":[{"Sensor":"Air Temperature D1","ParameterCode":"D1","Values":[264.0]},{"Sensor":"Water Temperature E1","ParameterCode":"E1","Values":[298.0]},{"Sensor":"Barometric Pressure F1","ParameterCode":"F1","Values":[3000.0]},{"Sensor":"ANALOG SENSOR 1","ParameterCode":"L1","Values":[140.0]},{"Sensor":"ANALOG SENSOR 2","ParameterCode":"M1","Values":[138.0]},{"Sensor":"Tsunami WL U1","ParameterCode":"U1","Values":[3465.0,3453.0,3457.0,3460.0,3473.0,3467.0]},{"Sensor":"Microwave WL Y1","ParameterCode":"Y1","Values":[3490.0]},{"Sensor":"Backup WL B1","ParameterCode":"B1","Values":[1281.0]},{"Sensor":"ANALOG SENSOR 1","ParameterCode":"L1","Values":[139.0]}],"EndTime":"2023-03-28 16:06:00.000+0000"}}