{"DomsatSeq":81181,"DomsatTime":0,"CarrierStart":"2023-04-13T04:33:00+00:00","CarrierStop":"2023-04-13T04:33:03+00:00","Baud":300,"GoodPhasePct":100,"FreqOffset":-1.1,"SignalStrength":40.6,"PhaseNoise":2.16,"LocalRecvTime":"2023-04-13T04:33:11+00:00","BinaryMsg":"MzNBMDc0N0UyMzEwMzA0MzMwMEc0MS0wTk4wNjlFVVAwMDA4MSJQODcyMjk1NjFCcWNAR0BAWDBaXkQ4QG9DQEdDI0BvTDRDdTVETTZhYD1BPzxCQzJAWUlAQ0AiQFlDPEJEIGRURFpMQEZARUBLQE5ASkBRIA==","flags":"0x00081855","platformId":"33A0747E","sat":"goes","agency":"NOANOS","DecodedData":{"Platform":"87229561-South Port Everglades (DCP 1)","TransportMedium":"goes-33A0747E","Station":"87229561","Sensors":[{"Sensor":"Air Temperature D1","ParameterCode":"D1","Values":[245.0]},{"Sensor":"Water Temperature E1","ParameterCode":"E1","Values":[269.0]},{"Sensor":"Barometric Pressure F1","ParameterCode":"F1","Values":[2944.0]},{"Sensor":"ANALOG SENSOR 1","ParameterCode":"L1","Values":[131.0]},{"Sensor":"ANALOG SENSOR 2","ParameterCode":"M1","Values":[127.0]},{"Sensor":"Tsunami WL U1","ParameterCode":"U1","Values":[3006.0,3005.0,3011.0,3014.0,3010.0,3017.0]},{"Sensor":"Microwave WL Y1","ParameterCode":"Y1","Values":[3020.0]},{"Sensor":"Backup WL B1","ParameterCode":"B1","Values":[1603.0]},{"Sensor":"ANALOG SENSOR 1","ParameterCode":"L1","Values":[132.0]}],"EndTime":"2023-04-13 04:24:00.000+0000"}}